sc.galleria.support-1.0.1-py2.7-nspkg.pth
sc/galleria/support/__init__.py
sc/galleria/support/config.py
sc/galleria/support/configure.zcml
sc/galleria/support/interfaces.py
sc/galleria/support/setuphandlers.py
sc/galleria/support/testing.py
sc/galleria/support/upgrades.zcml
sc/galleria/support/Extensions/Install.py
sc/galleria/support/Extensions/__init__.py
sc/galleria/support/browser/__init__.py
sc/galleria/support/browser/configure.zcml
sc/galleria/support/browser/galleria.py
sc/galleria/support/browser/images/dummy.png
sc/galleria/support/browser/images/galleriaicon.png
sc/galleria/support/browser/plugins/facebook/galleria.facebook.js
sc/galleria/support/browser/plugins/facebook/galleria.facebook.min.js
sc/galleria/support/browser/plugins/facebook/loader.gif
sc/galleria/support/browser/templates/galleria_view.pt
sc/galleria/support/browser/templates/galleriacollection_view.pt
sc/galleria/support/browser/templates/galleriamacros.pt
sc/galleria/support/locales/manual.pot
sc/galleria/support/locales/sc.galleria.support.pot
sc/galleria/support/locales/es/LC_MESSAGES/sc.galleria.support.po
sc/galleria/support/locales/pt_BR/LC_MESSAGES/sc.galleria.support.po
sc/galleria/support/profiles/default/actionicons.xml
sc/galleria/support/profiles/default/browserlayer.xml
sc/galleria/support/profiles/default/controlpanel.xml
sc/galleria/support/profiles/default/metadata.xml
sc/galleria/support/profiles/default/registry.xml
sc/galleria/support/profiles/default/sc.galleria_default.txt
sc/galleria/support/profiles/default/types/Collection.xml
sc/galleria/support/profiles/default/types/Folder.xml
sc/galleria/support/profiles/default/types/Link.xml
sc/galleria/support/profiles/default/types/Topic.xml
sc/galleria/support/profiles/uninstall/browserlayer.xml
sc/galleria/support/profiles/uninstall/controlpanel.xml
sc/galleria/support/profiles/uninstall/registry.xml
sc/galleria/support/profiles/uninstall/sc.galleria.support_uninstall.txt
sc.galleria.support-1.0.1.dist-info/DESCRIPTION.rst
sc.galleria.support-1.0.1.dist-info/METADATA
sc.galleria.support-1.0.1.dist-info/RECORD
sc.galleria.support-1.0.1.dist-info/WHEEL
sc.galleria.support-1.0.1.dist-info/entry_points.txt
sc.galleria.support-1.0.1.dist-info/metadata.json
sc.galleria.support-1.0.1.dist-info/namespace_packages.txt
sc.galleria.support-1.0.1.dist-info/top_level.txt
