Metadata-Version: 2.0
Name: sc.galleria.support
Version: 1.0.1
Summary: Simple gallery for Plone based in http://galleria.io
Home-page: http://www.simplesconsultoria.com.br
Author: Simples Consultoria
Author-email: products@simplesconsultoria.com.br
License: GPL
Keywords: python simples_consultoria plone galleria gallery
Platform: UNKNOWN
Classifier: Development Status :: 7 - Inactive
Classifier: Environment :: Web Environment
Classifier: Framework :: Plone
Classifier: Framework :: Plone :: 4.2
Classifier: Framework :: Plone :: 4.3
Classifier: Intended Audience :: System Administrators
Classifier: License :: OSI Approved :: GNU General Public License (GPL)
Classifier: Operating System :: OS Independent
Classifier: Programming Language :: JavaScript
Classifier: Programming Language :: Python
Classifier: Programming Language :: Python :: 2.6
Classifier: Programming Language :: Python :: 2.7
Classifier: Topic :: Software Development :: Libraries :: Python Modules
Requires-Dist: collective.js.galleria
Requires-Dist: plone.app.registry
Requires-Dist: setuptools
Provides-Extra: test
Requires-Dist: plone.app.testing; extra == 'test'
Requires-Dist: unittest2; extra == 'test'
